{
  "validation_sessions": {
    "WP-1-Spec-Appendices-Backfill-v1": {
      "wpId": "WP-1-Spec-Appendices-Backfill-v1",
      "verdict": "PASS",
      "status": "COMMITTED",
      "started": "2026-03-04T21:53:47.767Z",
      "gates": [
        {
          "gate": "WP_APPENDED",
          "verdict": "PASS",
          "timestamp": "2026-03-04T21:53:47.767Z"
        },
        {
          "gate": "COMMITTED",
          "timestamp": "2026-03-04T21:53:54.195Z"
        }
      ]
    }
  },
  "archived_sessions": []
}
