{
  "db_name": "SQLite",
  "query": "\n            UPDATE workflow_runs\n            SET status = $1,\n                updated_at = $2\n            WHERE id = $3\n            RETURNING\n                id as \"id!: String\",\n                job_id as \"job_id!: String\",\n                status as \"status!: String\",\n                created_at as \"created_at!: chrono::DateTime<chrono::Utc>\",\n                updated_at as \"updated_at!: chrono::DateTime<chrono::Utc>\"\n            ",
  "describe": {
    "columns": [
      {
        "name": "id!: String",
        "ordinal": 0,
        "type_info": "Text"
      },
      {
        "name": "job_id!: String",
        "ordinal": 1,
        "type_info": "Text"
      },
      {
        "name": "status!: String",
        "ordinal": 2,
        "type_info": "Text"
      },
      {
        "name": "created_at!: chrono::DateTime<chrono::Utc>",
        "ordinal": 3,
        "type_info": "Datetime"
      },
      {
        "name": "updated_at!: chrono::DateTime<chrono::Utc>",
        "ordinal": 4,
        "type_info": "Datetime"
      }
    ],
    "parameters": {
      "Right": 3
    },
    "nullable": [
      false,
      false,
      false,
      false,
      false
    ]
  },
  "hash": "8dbc3659224d5e14ced0febf65083be3ae05a40c6505f6bbc30ccaeb7209a6f9"
}
